atomflow/__init__.py
atomflow/__main__.py
atomflow/aspects/__init__.py
atomflow/aspects/__pycache__/__init__.cpython-313.pyc
atomflow/aspects/__pycache__/aspects.cpython-313-pytest-9.0.2.pyc
atomflow/aspects/__pycache__/aspects.cpython-313.pyc
atomflow/aspects/aspects.py
atomflow/atom/__init__.py
atomflow/atom/__pycache__/__init__.cpython-313.pyc
atomflow/atom/__pycache__/atom.cpython-313-pytest-9.0.2.pyc
atomflow/atom/__pycache__/atom.cpython-313.pyc
atomflow/atom/atom.py
atomflow/components/__init__.py
atomflow/components/__pycache__/__init__.cpython-313.pyc
atomflow/components/__pycache__/components.cpython-313.pyc
atomflow/components/components.py
atomflow/formats/__init__.py
atomflow/formats/__pycache__/__init__.cpython-313.pyc
atomflow/formats/__pycache__/cif.cpython-313-pytest-9.0.2.pyc
atomflow/formats/__pycache__/cif.cpython-313.pyc
atomflow/formats/__pycache__/fasta.cpython-313.pyc
atomflow/formats/__pycache__/format.cpython-313.pyc
atomflow/formats/__pycache__/pdb.cpython-313.pyc
atomflow/formats/cif.py
atomflow/formats/fasta.py
atomflow/formats/format.py
atomflow/formats/pdb.py
atomflow/iterator/__init__.py
atomflow/iterator/__pycache__/__init__.cpython-313.pyc
atomflow/iterator/__pycache__/iterator.cpython-313.pyc
atomflow/iterator/iterator.py
atomflow/knowledge/__init__.py
atomflow/knowledge/__pycache__/__init__.cpython-313.pyc
atomflow/knowledge/__pycache__/codes.cpython-313.pyc
atomflow/knowledge/codes.py
atomflow-0.2.0.dist-info/METADATA
atomflow-0.2.0.dist-info/WHEEL
atomflow-0.2.0.dist-info/RECORD
