Metadata-Version: 2.3
Name: atomflow
Version: 0.2.0
Summary: 
Author: bjtha
Author-email: 142571425+bjtha@users.noreply.github.com
Requires-Python: >=3.13,<4.0
Classifier: Programming Language :: Python :: 3
Classifier: Programming Language :: Python :: 3.13
